okx_trade/__init__.py
okx_trade/code/__init__.py
okx_trade/code/account.py
okx_trade/code/execute.py
okx_trade/code/market.py
okx_trade/code/trade.py
okx_trade/exception/__init__.py
okx_trade/exception/_base.py
okx_trade/exception/param.py
okx_trade/exception/req.py
okx_trade/exception/rule.py
okx_trade/exception/unexpected.py
okx_trade/okx_spot/__init__.py
okx_trade/okx_spot/account/__init__.py
okx_trade/okx_spot/market/__init__.py
okx_trade/okx_spot/trade/__init__.py
okx_trade/okx_spot/trade/_base.py
okx_trade/okx_spot/trade/close.py
okx_trade/okx_spot/trade/open.py
okx_trade/okx_spot/trade/order.py
okx_trade/okx_spot/trade/quantity_and_price.py
okx_trade/okx_swap/__init__.py
okx_trade/okx_swap/account/__init__.py
okx_trade/okx_swap/market/__init__.py
okx_trade/okx_swap/trade/__init__.py
okx_trade/okx_swap/trade/_base.py
okx_trade/okx_swap/trade/close.py
okx_trade/okx_swap/trade/open.py
okx_trade/okx_swap/trade/order.py
okx_trade/okx_swap/trade/quantity_and_price.py
okx_trade-1.0.2.dist-info/METADATA
okx_trade-1.0.2.dist-info/WHEEL
okx_trade-1.0.2.dist-info/top_level.txt
okx_trade-1.0.2.dist-info/RECORD
