Metadata-Version: 2.1
Name: okx-trade
Version: 1.0.2
Summary: Make OKX API Transactions Easier
Home-page: https://github.com/pyted/okx_trade
Author: pyted
Author-email: pyted@outlook.com
License: MIT
Classifier: License :: OSI Approved :: MIT License
Classifier: Programming Language :: Python
Classifier: Programming Language :: Python :: 3
Classifier: Programming Language :: Python :: 3.6
Classifier: Programming Language :: Python :: Implementation :: CPython
Classifier: Programming Language :: Python :: Implementation :: PyPy
Requires-Python: >=3.6.0
Requires-Dist: candlelite
Requires-Dist: paux (>=1.0.5)
Requires-Dist: okx (>=1.0.7)
Requires-Dist: okx-candle (>=1.0.5)
